genpixel-hello/__init__.py
genpixel-hello/main.py
genpixel_hello/__init__.py
genpixel_hello/main.py
src/__init__.py
src/main.py
genpixel-0.0.3.dist-info/METADATA
genpixel-0.0.3.dist-info/WHEEL
genpixel-0.0.3.dist-info/top_level.txt
genpixel-0.0.3.dist-info/RECORD
