Metadata-Version: 2.1
Name: genpixel
Version: 0.0.3
Author: okela
Requires-Dist: setuptools
Requires-Dist: wheel
Requires-Dist: twine
